summit_counter/__init__.py
summit_counter/main.py
summit_counter/ptg.py
openstack_summit_counter-0.4.0.dist-info/AUTHORS
openstack_summit_counter-0.4.0.dist-info/LICENSE
openstack_summit_counter-0.4.0.dist-info/METADATA
openstack_summit_counter-0.4.0.dist-info/WHEEL
openstack_summit_counter-0.4.0.dist-info/entry_points.txt
openstack_summit_counter-0.4.0.dist-info/pbr.json
openstack_summit_counter-0.4.0.dist-info/top_level.txt
openstack_summit_counter-0.4.0.dist-info/RECORD
