Metadata-Version: 2.1
Name: openstack-summit-counter
Version: 0.4.0
Summary: OSC Plugin to help compute the number of summits someone has attended.
Home-page: https://pypi.python.org/pypi/openstack-summit-counter
Author: Doug Hellmann
Author-email: doug@doughellmann.com
License: UNKNOWN
Platform: UNKNOWN
Classifier: Environment :: Console
Classifier: Environment :: OpenStack
Classifier: Intended Audience :: Information Technology
Classifier: License :: OSI Approved :: Apache Software License
Classifier: Programming Language :: Python
Classifier: Programming Language :: Python :: 3
Requires-Dist: pbr (!=2.1.0,>=2.0.0)
Requires-Dist: python-openstackclient (>=3.12.0)
